pydit/__init__.py
pydit/filemanager.py
pydit/functions/__init__.py
pydit/functions/anonymise.py
pydit/functions/blanks.py
pydit/functions/calendar_table.py
pydit/functions/cleanup_dataframe_columns_names.py
pydit/functions/coalesce_dataframe_columns.py
pydit/functions/coalesce_dataframe_values.py
pydit/functions/collapse_dataframe_levels.py
pydit/functions/counts.py
pydit/functions/date_time_calculations.py
pydit/functions/duplicates.py
pydit/functions/fillna.py
pydit/functions/fuzzy_matching.py
pydit/functions/groupby_text_concatenate.py
pydit/functions/keyword_search_batch.py
pydit/functions/lookup_values.py
pydit/functions/map_common_values.py
pydit/functions/merge.py
pydit/functions/referential_integrity_check.py
pydit/functions/sequence.py
pydit/functions/split_transactions.py
pydit/functions/truncate_datetime.py
pydit/functions/various.py
pydit/logger.py
pydit/statistics/__init__.py
pydit/statistics/benford.py
pydit/statistics/percentile.py
pydit/statistics/profile_dataframe_statistics.py
pydit/statistics/simulation.py
pydit_jceresearch-0.1.8.dist-info/LICENSE
pydit_jceresearch-0.1.8.dist-info/METADATA
pydit_jceresearch-0.1.8.dist-info/WHEEL
pydit_jceresearch-0.1.8.dist-info/RECORD
