Metadata-Version: 2.1
Name: pydit-jceresearch
Version: 0.1.8
Summary: Data cleansing tools for Internal Auditors
License: MIT
Keywords: internal audit,munging,cleansing,audit,wrangling,pandas
Author: jceresearch
Author-email: jceresearch@users.noreply.github.com
Requires-Python: >=3.12.7,<4.0.0
Classifier: Development Status :: 3 - Alpha
Classifier: License :: OSI Approved :: MIT License
Classifier: Programming Language :: Python :: 3
Classifier: Programming Language :: Python :: 3.13
Classifier: Programming Language :: Python :: 3 :: Only
Requires-Dist: matplotlib (>=3.8.0,<4.0.0)
Requires-Dist: numpy (>=1.25.2,<2.0.0)
Requires-Dist: openpyxl (>=3.1.2,<4.0.0)
Requires-Dist: pandas (>=2.0.3,<3.0.0)
Project-URL: Documentation, https://pydit.readthedocs.io/en/latest/
